{"cameraMode":{"drawMode":0,"name":"Shaded","section":"Shading Mode"},"sceneLighting":false,"audioPlay":false,"sceneViewState":{"m_AlwaysRefresh":false,"showFog":true,"showSkybox":false,"showFlares":true,"showImageEffects":true,"showParticleSystems":true,"showVisualEffectGraphs":true,"m_FxEnabled":true},"in2DMode":false,"pivot":{"x":-2.1176185607910158,"y":8.134353637695313,"z":2.3069591522216799},"rotation":{"x":-0.11692718416452408,"y":0.7583009004592896,"z":-0.1417587548494339,"w":-0.6254695653915405},"size":40.62834167480469,"orthographic":false}